{"title":"Anal.Plungers.2.XXX.DVDRiP.x264-PORNOLATiON","uid":8417954,"size":2159894244,"categoryP":"porn","categoryS":"movies","magnet":"?xt=urn:btih:03ee75e1981e215976292d40a97e273a1850d396&amp;dn=Anal.Plungers.2.XXX.DVDRiP.x264-PORNOLATiON&amp;tr=udp%3A%2F%2Ftracker.openbittorrent.com%3A80&amp;tr=udp%3A%2F%2Fopen.demonii.com%3A1337&amp;tr=udp%3A%2F%2Ftracker.coppersurfer.tk%3A6969&amp;tr=udp%3A%2F%2Fexodus.desync.com%3A6969","seeders":0,"leechers":0,"uploader":"ntkmedia","files":1,"time":1367098614,"description":"Title: Anal Plungers 2 - Jules Jordans Ass Factory\nRelease date: 27 April 2013\nStore Release: 17 April 2013\nSource Format: NTSC DVD\nFormat: x264 @ crf 20\nResolution: 16:9\nAudio: AAC-LC\nLanguage: English\nCategory: Anal\n &lt;a href=&quot;\nhttp://www.pixdump.me/viewer.php?file=cay28w77ikihohg0uvwx.jpg&quot; rel=&quot;nofollow&quot; target=&quot;_NEW&quot;&gt;\nhttp://www.pixdump.me/viewer.php?file=cay28w77ikihohg0uvwx.jpg&lt;/a&gt;\n\n-NTK-","torrent":{"xt":"urn:btih:03ee75e1981e215976292d40a97e273a1850d396","amp;dn":"Anal.Plungers.2.XXX.DVDRiP.x264-PORNOLATiON","amp;tr":["udp%3A%2F%2Ftracker.openbittorrent.com%3A80","udp%3A%2F%2Fopen.demonii.com%3A1337","udp%3A%2F%2Ftracker.coppersurfer.tk%3A6969","udp%3A%2F%2Fexodus.desync.com%3A6969"],"infoHash":"03ee75e1981e215976292d40a97e273a1850d396","infoHashBuffer":{"type":"Buffer","data":[3,238,117,225,152,30,33,89,118,41,45,64,169,126,39,58,24,80,211,150]},"announce":[],"urlList":[]}}