{"title":"BustyCafe  10 06 09 Carol Goldnerova Oiled Big Boobs  iMAGEsET","uid":8386957,"size":22730963,"categoryP":"porn","categoryS":"pictures","magnet":"?xt=urn:btih:0ba8fa14af47459e7d27a84016acad01a1e96379&amp;dn=+BustyCafe++10+06+09+Carol+Goldnerova+Oiled+Big+Boobs++iMAGEsET+&amp;tr=udp%3A%2F%2Ftracker.openbittorrent.com%3A80&amp;tr=udp%3A%2F%2Fopen.demonii.com%3A1337&amp;tr=udp%3A%2F%2Ftracker.coppersurfer.tk%3A6969&amp;tr=udp%3A%2F%2Fexodus.desync.com%3A6969","seeders":0,"leechers":1,"uploader":"legend79023","files":101,"time":1366309349,"description":"      ~ [BustyCafe]  10 06 09 Carol Goldnerova Oiled Big Boobs  iMAGEsET - ExtraTorrentAT ~\n\n\n            Please Seed After Download!","torrent":{"xt":"urn:btih:0ba8fa14af47459e7d27a84016acad01a1e96379","amp;dn":"+BustyCafe++10+06+09+Carol+Goldnerova+Oiled+Big+Boobs++iMAGEsET+","amp;tr":["udp%3A%2F%2Ftracker.openbittorrent.com%3A80","udp%3A%2F%2Fopen.demonii.com%3A1337","udp%3A%2F%2Ftracker.coppersurfer.tk%3A6969","udp%3A%2F%2Fexodus.desync.com%3A6969"],"infoHash":"0ba8fa14af47459e7d27a84016acad01a1e96379","infoHashBuffer":{"type":"Buffer","data":[11,168,250,20,175,71,69,158,125,39,168,64,22,172,173,1,161,233,99,121]},"announce":[],"urlList":[]}}