{"title":"Markus Schulz - World Tour Kuala Lumpur (09 May 2013)","uid":8458852,"size":284389277,"categoryP":"audio","categoryS":"music","magnet":"?xt=urn:btih:13afaf8de18b52ceab2c6635f1c6524c312a9d35&amp;dn=Markus+Schulz+-+World+Tour+Kuala+Lumpur+%2809+May+2013%29&amp;tr=udp%3A%2F%2Ftracker.openbittorrent.com%3A80&amp;tr=udp%3A%2F%2Fopen.demonii.com%3A1337&amp;tr=udp%3A%2F%2Ftracker.coppersurfer.tk%3A6969&amp;tr=udp%3A%2F%2Fexodus.desync.com%3A6969","seeders":0,"leechers":0,"uploader":"nesmeured","files":-1,"time":1368175994,"description":"\n\n\n AUDiO\n\n\n Bitrate : 320 kb/s (CBR)\n Codec : LAME\n Samplerate : 44.1 kHz\n Channels : Stereo (Full)\n Bitdepth : 16-bit\n Genre : Trance | Progressive\n Source: Transcoded from MixCloud 96 kb/s AAC+ Podcast\n\n\n\n\n OTHER iNFO\n\n\n Markus Schulz (118:29 Mins)\n\n 01.Markus Schulz - Our Moment (Scream Tour Intro)\n\n 02.New World Punx - Romper\n\n 03.Ferry Corsten &amp; Bassjackers - Collision\n\n 04.Omnia - The Light\n\n 05.Markus Schulz feat. Sarah Howells - Tempted\n\n 06.Mark Sixma - Requiem\n\n 07.Markus Schulz feat. Ken Spector - Scream\n\n 08.Aerofoil vs. E&amp;G - One Word (Markus Schulz big room reconstruction)\n\n 09.Dimitri Vegas, Moguai &amp; Like Mike vs. Ferry Corsten &amp; Aruna - Mammoth Forever (New World Punx mashup)\n\n 10.ID\n\n 11.Armin van Buuren vs. W&amp;W - D# Fat\n\n 12.ID\n\n 13.Fisherman &amp; Hawkins - Apache\n\n 14.Markus Schulz - The Spiritual Gateway\n\n 15.Markus Schulz feat. Ana Diaz - Nothing Without Me (Beat Service remix)\n\n 16.Cosmic Gate - Storm Chaser (Khomha remix)\n\n 17.Grube &amp; Hovsepian - Trickster\n\n 18.Beat Service - Fortuna\n\n 19.Markus Schulz - The New World 2013\n\n 20.Markus Schulz vs. Sander van Doorn vs. Nero - Chasin' the Same Promises (Markus Schulz mashup)\n\n 21.Beat Service - Impulse\n\n 22.ID\n\n 23.Markus Schulz &amp; Ferry Corsten - Loops &amp; Tings\n\n 24.BINARY FINARY - 1998 (New World Punx remix)\n\n 25.ID\n\n 26.Solarstone - Solarcoaster (Remix)\n\n 27.ID\n\n 28.Omnia &amp; Ira vs. Bingo Players vs. Hardwell - Mindfused Spaceman (Markus Schulz mashup)\n\n 29.New World Punx - Digital Dreaming Punk\n\n 30.Markus Schulz feat. Seri - Love Rain Down (4 Strings remix)\n\n\n\n\t  S\t  A\t   L\t   U\t   T\t   E\n\t\n\tViSiON\t\t     AiR\t\t SANTi\n\t\n\n\n\n\n nesmeured encoded !\n","torrent":{"xt":"urn:btih:13afaf8de18b52ceab2c6635f1c6524c312a9d35","amp;dn":"Markus+Schulz+-+World+Tour+Kuala+Lumpur+%2809+May+2013%29","amp;tr":["udp%3A%2F%2Ftracker.openbittorrent.com%3A80","udp%3A%2F%2Fopen.demonii.com%3A1337","udp%3A%2F%2Ftracker.coppersurfer.tk%3A6969","udp%3A%2F%2Fexodus.desync.com%3A6969"],"infoHash":"13afaf8de18b52ceab2c6635f1c6524c312a9d35","infoHashBuffer":{"type":"Buffer","data":[19,175,175,141,225,139,82,206,171,44,102,53,241,198,82,76,49,42,157,53]},"announce":[],"urlList":[]}}