{"title":"Vanessa Cage - This Never Happened (2013) ","uid":8338177,"size":227875321,"categoryP":"porn","categoryS":"movie_clips","magnet":"?xt=urn:btih:164e0a64b9de34fe62cc40bcdf92a967ac6704ef&amp;dn=Vanessa+Cage+-+This+Never+Happened+%282013%29+&amp;tr=udp%3A%2F%2Ftracker.openbittorrent.com%3A80&amp;tr=udp%3A%2F%2Fopen.demonii.com%3A1337&amp;tr=udp%3A%2F%2Ftracker.coppersurfer.tk%3A6969&amp;tr=udp%3A%2F%2Fexodus.desync.com%3A6969","seeders":0,"leechers":1,"uploader":"Programsmith","files":1,"time":1365025766,"description":"Gallery and Description:\n &lt;a href=&quot;\nhttp://extraload.net/viewtopic.php?f=9&amp;t=573&quot; rel=&quot;nofollow&quot; target=&quot;_NEW&quot;&gt;\nhttp://extraload.net/viewtopic.php?f=9&amp;t=573&lt;/a&gt;","torrent":{"xt":"urn:btih:164e0a64b9de34fe62cc40bcdf92a967ac6704ef","amp;dn":"Vanessa+Cage+-+This+Never+Happened+%282013%29+","amp;tr":["udp%3A%2F%2Ftracker.openbittorrent.com%3A80","udp%3A%2F%2Fopen.demonii.com%3A1337","udp%3A%2F%2Ftracker.coppersurfer.tk%3A6969","udp%3A%2F%2Fexodus.desync.com%3A6969"],"infoHash":"164e0a64b9de34fe62cc40bcdf92a967ac6704ef","infoHashBuffer":{"type":"Buffer","data":[22,78,10,100,185,222,52,254,98,204,64,188,223,146,169,103,172,103,4,239]},"announce":[],"urlList":[]}}