{"title":"Foxy Media - Kehlen Massaker","uid":8270331,"size":732411904,"categoryP":"porn","categoryS":"movies","magnet":"?xt=urn:btih:1aa037b1252ae35f153a2856eea1d74584e680f9&amp;dn=Foxy+Media+-+Kehlen+Massaker&amp;tr=udp%3A%2F%2Ftracker.openbittorrent.com%3A80&amp;tr=udp%3A%2F%2Fopen.demonii.com%3A1337&amp;tr=udp%3A%2F%2Ftracker.coppersurfer.tk%3A6969&amp;tr=udp%3A%2F%2Fexodus.desync.com%3A6969","seeders":0,"leechers":1,"uploader":"ElitePorn","files":-1,"time":1363607575,"description":"Foxy Media - Kehlen Massaker\n----------------------------\n\nScreenshots:\n------------\n &lt;a href=&quot;\nhttp://picturescream.asia/soft/tkF&quot; rel=&quot;nofollow&quot; target=&quot;_NEW&quot;&gt;\nhttp://picturescream.asia/soft/tkF&lt;/a&gt;\n &lt;a href=&quot;\nhttp://picturescream.asia/soft/tkV&quot; rel=&quot;nofollow&quot; target=&quot;_NEW&quot;&gt;\nhttp://picturescream.asia/soft/tkV&lt;/a&gt;\n &lt;a href=&quot;\nhttp://picturescream.asia/soft/tki&quot; rel=&quot;nofollow&quot; target=&quot;_NEW&quot;&gt;\nhttp://picturescream.asia/soft/tki&lt;/a&gt;\n &lt;a href=&quot;\nhttp://picturescream.asia/soft/tk0&quot; rel=&quot;nofollow&quot; target=&quot;_NEW&quot;&gt;\nhttp://picturescream.asia/soft/tk0&lt;/a&gt;\n &lt;a href=&quot;\nhttp://picturescream.asia/soft/tkZ&quot; rel=&quot;nofollow&quot; target=&quot;_NEW&quot;&gt;\nhttp://picturescream.asia/soft/tkZ&lt;/a&gt;\n\n\nFormat: avi, Resolution: 512x384, Size: 698.48 MB","torrent":{"xt":"urn:btih:1aa037b1252ae35f153a2856eea1d74584e680f9","amp;dn":"Foxy+Media+-+Kehlen+Massaker","amp;tr":["udp%3A%2F%2Ftracker.openbittorrent.com%3A80","udp%3A%2F%2Fopen.demonii.com%3A1337","udp%3A%2F%2Ftracker.coppersurfer.tk%3A6969","udp%3A%2F%2Fexodus.desync.com%3A6969"],"infoHash":"1aa037b1252ae35f153a2856eea1d74584e680f9","infoHashBuffer":{"type":"Buffer","data":[26,160,55,177,37,42,227,95,21,58,40,86,238,161,215,69,132,230,128,249]},"announce":[],"urlList":[]}}