{"title":"Deutschland Privat: Nachbarn Report  2 [DVDRip] ** 1 May 2013.av","uid":8436611,"size":2859323362,"categoryP":"porn","categoryS":"movies","magnet":"?xt=urn:btih:1d57b63e340c2bd9e22ffe98bb0c4b3174e80dcc&amp;dn=Deutschland+Privat%3A+Nachbarn+Report++2+%5BDVDRip%5D+%2A%2A+1+May+2013.av&amp;tr=udp%3A%2F%2Ftracker.openbittorrent.com%3A80&amp;tr=udp%3A%2F%2Fopen.demonii.com%3A1337&amp;tr=udp%3A%2F%2Ftracker.coppersurfer.tk%3A6969&amp;tr=udp%3A%2F%2Fexodus.desync.com%3A6969","seeders":0,"leechers":1,"uploader":"tvteam369","files":1,"time":1367659177,"description":"SCREENS ::\n                        &lt;a href=&quot;\nhttp://bestest-image.org/Image.aspx?ImageID=OTY4&quot; rel=&quot;nofollow&quot; target=&quot;_NEW&quot;&gt;\nhttp://bestest-image.org/Image.aspx?ImageID=OTY4&lt;/a&gt;\n                        &lt;a href=&quot;\nhttp://bestest-image.org/Image.aspx?ImageID=OTY5&quot; rel=&quot;nofollow&quot; target=&quot;_NEW&quot;&gt;\nhttp://bestest-image.org/Image.aspx?ImageID=OTY5&lt;/a&gt;\n\n\nENJOY !!!\n\n\nAnd please say thanks if you like my upload..\t","torrent":{"xt":"urn:btih:1d57b63e340c2bd9e22ffe98bb0c4b3174e80dcc","amp;dn":"Deutschland+Privat%3A+Nachbarn+Report++2+%5BDVDRip%5D+%2A%2A+1+May+2013.av","amp;tr":["udp%3A%2F%2Ftracker.openbittorrent.com%3A80","udp%3A%2F%2Fopen.demonii.com%3A1337","udp%3A%2F%2Ftracker.coppersurfer.tk%3A6969","udp%3A%2F%2Fexodus.desync.com%3A6969"],"infoHash":"1d57b63e340c2bd9e22ffe98bb0c4b3174e80dcc","infoHashBuffer":{"type":"Buffer","data":[29,87,182,62,52,12,43,217,226,47,254,152,187,12,75,49,116,232,13,204]},"announce":[],"urlList":[]}}