{"title":"Thom Hartmann Program - May 15 2013","uid":8483134,"size":66705320,"categoryP":"audio","categoryS":"other","magnet":"?xt=urn:btih:1e641140f73ed9f00e87a8e2f2fe5e3833d0e815&amp;dn=Thom+Hartmann+Program+-+May+15+2013&amp;tr=udp%3A%2F%2Ftracker.openbittorrent.com%3A80&amp;tr=udp%3A%2F%2Fopen.demonii.com%3A1337&amp;tr=udp%3A%2F%2Ftracker.coppersurfer.tk%3A6969&amp;tr=udp%3A%2F%2Fexodus.desync.com%3A6969","seeders":0,"leechers":0,"uploader":"480v","files":3,"time":1368786574,"description":"May 15, 2013\nThe Thom Hartmann Program \n\nHour One: Memo to Bush Administration leftovers on Fox: Shut Up!\n\nHour Two: Where will the class be held on &quot;stoning people to death&quot; for worshiping the wrong god?  Pastor Josh Moore, First Baptist Church of Muldrow, OK / Plus, no more trade deal sellouts!  Congressman Alan Grayson (D-FL, 9th District)\n\nHour Three: Hey AP, first they came for Wikileaks...where were you?","torrent":{"xt":"urn:btih:1e641140f73ed9f00e87a8e2f2fe5e3833d0e815","amp;dn":"Thom+Hartmann+Program+-+May+15+2013","amp;tr":["udp%3A%2F%2Ftracker.openbittorrent.com%3A80","udp%3A%2F%2Fopen.demonii.com%3A1337","udp%3A%2F%2Ftracker.coppersurfer.tk%3A6969","udp%3A%2F%2Fexodus.desync.com%3A6969"],"infoHash":"1e641140f73ed9f00e87a8e2f2fe5e3833d0e815","infoHashBuffer":{"type":"Buffer","data":[30,100,17,64,247,62,217,240,14,135,168,226,242,254,94,56,51,208,232,21]},"announce":[],"urlList":[]}}