{"title":"AllOver30.13.05.03.Christy.XXX.720p.WMV-GAGViD","uid":8436772,"size":372572781,"categoryP":"porn","categoryS":"other","magnet":"?xt=urn:btih:227503fde9e4527b61694d1fe284935799f877cf&amp;dn=AllOver30.13.05.03.Christy.XXX.720p.WMV-GAGViD&amp;tr=udp%3A%2F%2Ftracker.openbittorrent.com%3A80&amp;tr=udp%3A%2F%2Fopen.demonii.com%3A1337&amp;tr=udp%3A%2F%2Ftracker.coppersurfer.tk%3A6969&amp;tr=udp%3A%2F%2Fexodus.desync.com%3A6969","seeders":0,"leechers":0,"uploader":"Drarbg","files":4,"time":1367663944,"description":"AllOver30.13.05.03.Christy.XXX.720p.WMV-GAGViD\n-----------------------------------------\nScreens : &lt;a href=&quot;\nhttp://imagecurl.org/viewer.php?file=73637266917996076277.jpg&quot; rel=&quot;nofollow&quot; target=&quot;_NEW&quot;&gt;\nhttp://imagecurl.org/viewer.php?file=73637266917996076277.jpg&lt;/a&gt;\n\n","torrent":{"xt":"urn:btih:227503fde9e4527b61694d1fe284935799f877cf","amp;dn":"AllOver30.13.05.03.Christy.XXX.720p.WMV-GAGViD","amp;tr":["udp%3A%2F%2Ftracker.openbittorrent.com%3A80","udp%3A%2F%2Fopen.demonii.com%3A1337","udp%3A%2F%2Ftracker.coppersurfer.tk%3A6969","udp%3A%2F%2Fexodus.desync.com%3A6969"],"infoHash":"227503fde9e4527b61694d1fe284935799f877cf","infoHashBuffer":{"type":"Buffer","data":[34,117,3,253,233,228,82,123,97,105,77,31,226,132,147,87,153,248,119,207]},"announce":[],"urlList":[]}}