{"title":"Nvidia 263.09 WHQL","uid":8348651,"size":136482849,"categoryP":"applications","categoryS":"windows","magnet":"?xt=urn:btih:30aa81069a3145d57dc6b41b27cc5ddab6004706&amp;dn=Nvidia+263.09+WHQL&amp;tr=udp%3A%2F%2Ftracker.openbittorrent.com%3A80&amp;tr=udp%3A%2F%2Fopen.demonii.com%3A1337&amp;tr=udp%3A%2F%2Ftracker.coppersurfer.tk%3A6969&amp;tr=udp%3A%2F%2Fexodus.desync.com%3A6969","seeders":0,"leechers":0,"uploader":"geork96","files":5,"time":1365271237,"description":"Nvidia 263.09 WHQL","torrent":{"xt":"urn:btih:30aa81069a3145d57dc6b41b27cc5ddab6004706","amp;dn":"Nvidia+263.09+WHQL","amp;tr":["udp%3A%2F%2Ftracker.openbittorrent.com%3A80","udp%3A%2F%2Fopen.demonii.com%3A1337","udp%3A%2F%2Ftracker.coppersurfer.tk%3A6969","udp%3A%2F%2Fexodus.desync.com%3A6969"],"infoHash":"30aa81069a3145d57dc6b41b27cc5ddab6004706","infoHashBuffer":{"type":"Buffer","data":[48,170,129,6,154,49,69,213,125,198,180,27,39,204,93,218,182,0,71,6]},"announce":[],"urlList":[]}}