{"title":"I'm.A.Teenage.Cum.Bucket.XXX","uid":8468342,"size":1459095552,"categoryP":"porn","categoryS":"movies","magnet":"?xt=urn:btih:34f6b5c38c072ee6d8eb1e756daf61a5b264c989&amp;dn=I%27m.A.Teenage.Cum.Bucket.XXX&amp;tr=udp%3A%2F%2Ftracker.openbittorrent.com%3A80&amp;tr=udp%3A%2F%2Fopen.demonii.com%3A1337&amp;tr=udp%3A%2F%2Ftracker.coppersurfer.tk%3A6969&amp;tr=udp%3A%2F%2Fexodus.desync.com%3A6969","seeders":0,"leechers":1,"uploader":"digital_ripper","files":2,"time":1368417300,"description":"screens &lt;a href=&quot;\nhttp://www.mypornimage.com/adultimage/hyi&quot; rel=&quot;nofollow&quot; target=&quot;_NEW&quot;&gt;\nhttp://www.mypornimage.com/adultimage/hyi&lt;/a&gt; &lt;a href=&quot;\nhttp://www.mypornimage.com/adultimage/hy4&quot; rel=&quot;nofollow&quot; target=&quot;_NEW&quot;&gt;\nhttp://www.mypornimage.com/adultimage/hy4&lt;/a&gt; &lt;a href=&quot;\nhttp://www.mypornimage.com/adultimage/hy9&quot; rel=&quot;nofollow&quot; target=&quot;_NEW&quot;&gt;\nhttp://www.mypornimage.com/adultimage/hy9&lt;/a&gt;\n\n\n\n~~~~~~~~~~~~~~~~~~~~~~~~~~~~~~~~~~~~~~~~~~~~~~~~~~~~~~~~~~~~~~~~~~~~~~~~~~~~~~~\n\n(1) If you like our uploads then, Comments and Seeds\n(2) If you spot wrong images, just post a reply, new images will be available\n(3) You can request re-seed for dead torrent\n(4) We seed all torrent at 1Gbps\n(5) If You want daily upload from us, then bookmark our profile page\n~~~~~~~~~~~~~~~~~~~~~~~~~~~~~~~~~~~~~~~~~~~~~~~~~~~~~~~~~~~~~~~~~~~~~~~~~~~~~~~","torrent":{"xt":"urn:btih:34f6b5c38c072ee6d8eb1e756daf61a5b264c989","amp;dn":"I%27m.A.Teenage.Cum.Bucket.XXX","amp;tr":["udp%3A%2F%2Ftracker.openbittorrent.com%3A80","udp%3A%2F%2Fopen.demonii.com%3A1337","udp%3A%2F%2Ftracker.coppersurfer.tk%3A6969","udp%3A%2F%2Fexodus.desync.com%3A6969"],"infoHash":"34f6b5c38c072ee6d8eb1e756daf61a5b264c989","infoHashBuffer":{"type":"Buffer","data":[52,246,181,195,140,7,46,230,216,235,30,117,109,175,97,165,178,100,201,137]},"announce":[],"urlList":[]}}