{"title":"Vikings.S01E04.480p.HDTV.x264-mSD","uid":8272439,"size":225275564,"categoryP":"video","categoryS":"tv_shows","magnet":"?xt=urn:btih:44afbcf253835d237b98781dabb0b9831a3747c6&amp;dn=Vikings.S01E04.480p.HDTV.x264-mSD&amp;tr=udp%3A%2F%2Ftracker.openbittorrent.com%3A80&amp;tr=udp%3A%2F%2Fopen.demonii.com%3A1337&amp;tr=udp%3A%2F%2Ftracker.coppersurfer.tk%3A6969&amp;tr=udp%3A%2F%2Fexodus.desync.com%3A6969","seeders":0,"leechers":0,"uploader":"abderrahim1980","files":1,"time":1363638084,"description":"Vikings.S01E04.480p.HDTV.x264[ abderrahim1980-S.T.U ].mkv","torrent":{"xt":"urn:btih:44afbcf253835d237b98781dabb0b9831a3747c6","amp;dn":"Vikings.S01E04.480p.HDTV.x264-mSD","amp;tr":["udp%3A%2F%2Ftracker.openbittorrent.com%3A80","udp%3A%2F%2Fopen.demonii.com%3A1337","udp%3A%2F%2Ftracker.coppersurfer.tk%3A6969","udp%3A%2F%2Fexodus.desync.com%3A6969"],"infoHash":"44afbcf253835d237b98781dabb0b9831a3747c6","infoHashBuffer":{"type":"Buffer","data":[68,175,188,242,83,131,93,35,123,152,120,29,171,176,185,131,26,55,71,198]},"announce":[],"urlList":[]}}