{"title":"Big Ass Roundup XXX (DVDRip)","uid":8288848,"size":2203559936,"categoryP":"porn","categoryS":"movies","magnet":"?xt=urn:btih:47703770368e67f3992f19dae356466c4d8bbbf3&amp;dn=Big+Ass+Roundup+XXX+%28DVDRip%29&amp;tr=udp%3A%2F%2Ftracker.openbittorrent.com%3A80&amp;tr=udp%3A%2F%2Fopen.demonii.com%3A1337&amp;tr=udp%3A%2F%2Ftracker.coppersurfer.tk%3A6969&amp;tr=udp%3A%2F%2Fexodus.desync.com%3A6969","seeders":0,"leechers":1,"uploader":"xuluhulu","files":3,"time":1363994955,"description":"The legendary, recently late director John Leslie left a legacy of beautifully photographed hard-core cinema. He crafted scenes of bewitching lust by creating scenarios that allow viewers to apply their own erotic imagination; by casting gorgeous, sensual girls; and by giving his starlets the freedom to express their own sexual charms. Leslie's illustrious filmmaking career yielded enough exciting sex to fill any number of thematic compilations, and Big Ass Roundup is a robust example. The nine outstanding scenes of this double-disc DVD boast some of the XXX world's most bountifully butt-blessed talent in well over five hours of action.\n\nCOVERS:\n &lt;a href=&quot;\nhttp://imgnip.com/viewer.php?file=52861024990058396724.jpg&quot; rel=&quot;nofollow&quot; target=&quot;_NEW&quot;&gt;\nhttp://imgnip.com/viewer.php?file=52861024990058396724.jpg&lt;/a&gt;\n &lt;a href=&quot;\nhttp://imgnip.com/viewer.php?file=91098518949920342340.jpg&quot; rel=&quot;nofollow&quot; target=&quot;_NEW&quot;&gt;\nhttp://imgnip.com/viewer.php?file=91098518949920342340.jpg&lt;/a&gt;\n\n\nTHUMBSNAIL SCREENS:\n &lt;a href=&quot;\nhttp://imgnip.com/viewer.php?file=43229200137970948757.jpg&quot; rel=&quot;nofollow&quot; target=&quot;_NEW&quot;&gt;\nhttp://imgnip.com/viewer.php?file=43229200137970948757.jpg&lt;/a&gt;\n &lt;a href=&quot;\nhttp://imgnip.com/viewer.php?file=64557157289619305728.jpg&quot; rel=&quot;nofollow&quot; target=&quot;_NEW&quot;&gt;\nhttp://imgnip.com/viewer.php?file=64557157289619305728.jpg&lt;/a&gt;\n &lt;a href=&quot;\nhttp://imgnip.com/viewer.php?file=58741864495818290466.jpg&quot; rel=&quot;nofollow&quot; target=&quot;_NEW&quot;&gt;\nhttp://imgnip.com/viewer.php?file=58741864495818290466.jpg&lt;/a&gt;\n\n\nCAST:\n\nAlexis Texas, Phoenix Marie, Tori Black, Bobbi Starr, Jenny Hendrix, Brianna Love, Rachel Starr, Aline, Haileey James, Mr Pete, Tommy Gunn, Mark Wood, Marco Banderas, Rico Strong, Prince Yahshua, Jerry, Alec Knight, Johnny Sins, Aaron Wilcox, Joe Blow, Ice Cold\n\n\nSEED &amp; ENJOY!!!","torrent":{"xt":"urn:btih:47703770368e67f3992f19dae356466c4d8bbbf3","amp;dn":"Big+Ass+Roundup+XXX+%28DVDRip%29","amp;tr":["udp%3A%2F%2Ftracker.openbittorrent.com%3A80","udp%3A%2F%2Fopen.demonii.com%3A1337","udp%3A%2F%2Ftracker.coppersurfer.tk%3A6969","udp%3A%2F%2Fexodus.desync.com%3A6969"],"infoHash":"47703770368e67f3992f19dae356466c4d8bbbf3","infoHashBuffer":{"type":"Buffer","data":[71,112,55,112,54,142,103,243,153,47,25,218,227,86,70,108,77,139,187,243]},"announce":[],"urlList":[]}}