{"title":"Her-Sweet-Hand.13.03.20.Mystery.K.Trust.Me.She.Is.Beautiful.XXX.","uid":8294769,"size":246195511,"categoryP":"porn","categoryS":"other","magnet":"?xt=urn:btih:49846128c82628d707d5de0bd858773015c416aa&amp;dn=Her-Sweet-Hand.13.03.20.Mystery.K.Trust.Me.She.Is.Beautiful.XXX.&amp;tr=udp%3A%2F%2Ftracker.openbittorrent.com%3A80&amp;tr=udp%3A%2F%2Fopen.demonii.com%3A1337&amp;tr=udp%3A%2F%2Ftracker.coppersurfer.tk%3A6969&amp;tr=udp%3A%2F%2Fexodus.desync.com%3A6969","seeders":0,"leechers":1,"uploader":"Drarbg","files":4,"time":1364084355,"description":"Her-Sweet-Hand.13.03.20.Mystery.K.Trust.Me.She.Is.Beautiful.XXX.MP4-OHRLY\n-----------------------------------------\nScreens : &lt;a href=&quot;\nhttp://capbb.com/viewtopic.php?f=21&amp;t=1482&quot; rel=&quot;nofollow&quot; target=&quot;_NEW&quot;&gt;\nhttp://capbb.com/viewtopic.php?f=21&amp;t=1482&lt;/a&gt;\n\n","torrent":{"xt":"urn:btih:49846128c82628d707d5de0bd858773015c416aa","amp;dn":"Her-Sweet-Hand.13.03.20.Mystery.K.Trust.Me.She.Is.Beautiful.XXX.","amp;tr":["udp%3A%2F%2Ftracker.openbittorrent.com%3A80","udp%3A%2F%2Fopen.demonii.com%3A1337","udp%3A%2F%2Ftracker.coppersurfer.tk%3A6969","udp%3A%2F%2Fexodus.desync.com%3A6969"],"infoHash":"49846128c82628d707d5de0bd858773015c416aa","infoHashBuffer":{"type":"Buffer","data":[73,132,97,40,200,38,40,215,7,213,222,11,216,88,119,48,21,196,22,170]},"announce":[],"urlList":[]}}