{"title":"ALLA_SKA_BADA.ISO","uid":8436828,"size":4681461760,"categoryP":"video","categoryS":"movies_dvdr","magnet":"?xt=urn:btih:4fac9b04150e9573ef22b0fdecbe5dd103360be3&amp;dn=ALLA_SKA_BADA.ISO&amp;tr=udp%3A%2F%2Ftracker.openbittorrent.com%3A80&amp;tr=udp%3A%2F%2Fopen.demonii.com%3A1337&amp;tr=udp%3A%2F%2Ftracker.coppersurfer.tk%3A6969&amp;tr=udp%3A%2F%2Fexodus.desync.com%3A6969","seeders":0,"leechers":0,"uploader":"torggatan","files":1,"time":1367665550,"description":"ALLA_SKA_BADA.ISO galenskaparna genre teater enyoy","torrent":{"xt":"urn:btih:4fac9b04150e9573ef22b0fdecbe5dd103360be3","amp;dn":"ALLA_SKA_BADA.ISO","amp;tr":["udp%3A%2F%2Ftracker.openbittorrent.com%3A80","udp%3A%2F%2Fopen.demonii.com%3A1337","udp%3A%2F%2Ftracker.coppersurfer.tk%3A6969","udp%3A%2F%2Fexodus.desync.com%3A6969"],"infoHash":"4fac9b04150e9573ef22b0fdecbe5dd103360be3","infoHashBuffer":{"type":"Buffer","data":[79,172,155,4,21,14,149,115,239,34,176,253,236,190,93,209,3,54,11,227]},"announce":[],"urlList":[]}}