{"title":"[ButtPlays] Savannah Secret (Secret? No more! / v600034 / 05.09.","uid":8458244,"size":1963413774,"categoryP":"porn","categoryS":"hd___movies","magnet":"?xt=urn:btih:5665a4e575af8d1caef4b28bab07214ccddfd9dd&amp;dn=%5BButtPlays%5D+Savannah+Secret+%28Secret%3F+No+more%21+%2F+v600034+%2F+05.09.&amp;tr=udp%3A%2F%2Ftracker.openbittorrent.com%3A80&amp;tr=udp%3A%2F%2Fopen.demonii.com%3A1337&amp;tr=udp%3A%2F%2Ftracker.coppersurfer.tk%3A6969&amp;tr=udp%3A%2F%2Fexodus.desync.com%3A6969","seeders":0,"leechers":0,"uploader":"chkm8te","files":1,"time":1368156909,"description":"[ButtPlays] Savannah Secret (Secret? No more! / v600034 / 05.09.2013)\nres:1080p\n\nSavannah was very secretive About Sexual her habits, All Being Shy About Sharing details. But when she got in front of the cameras, she opened up quickly, revealing her deepest wishes and naughtiest secrets. Because Savannah loves anal sex, that is not a secret anymore ... and we were happy to learn about it! \n\nScreens:  &lt;a href=&quot;\nhttp://xxxhost.me/viewer.php?file=lltiqjh7ykucoytatrop.jpg&quot; rel=&quot;nofollow&quot; target=&quot;_NEW&quot;&gt;\nhttp://xxxhost.me/viewer.php?file=lltiqjh7ykucoytatrop.jpg&lt;/a&gt;\n  &lt;a href=&quot;\nhttp://xxxhost.me/viewer.php?file=5gtlea9tkuj1x7n3p7gn.jpg&quot; rel=&quot;nofollow&quot; target=&quot;_NEW&quot;&gt;\nhttp://xxxhost.me/viewer.php?file=5gtlea9tkuj1x7n3p7gn.jpg&lt;/a&gt;","torrent":{"xt":"urn:btih:5665a4e575af8d1caef4b28bab07214ccddfd9dd","amp;dn":"%5BButtPlays%5D+Savannah+Secret+%28Secret%3F+No+more%21+%2F+v600034+%2F+05.09.","amp;tr":["udp%3A%2F%2Ftracker.openbittorrent.com%3A80","udp%3A%2F%2Fopen.demonii.com%3A1337","udp%3A%2F%2Ftracker.coppersurfer.tk%3A6969","udp%3A%2F%2Fexodus.desync.com%3A6969"],"infoHash":"5665a4e575af8d1caef4b28bab07214ccddfd9dd","infoHashBuffer":{"type":"Buffer","data":[86,101,164,229,117,175,141,28,174,244,178,139,171,7,33,76,205,223,217,221]},"announce":[],"urlList":[]}}