{"title":"Bondi.Vet.S05E09.MQwebrip.xvid-][ Chris out on the Farm, Labour ","uid":8440595,"size":366095110,"categoryP":"video","categoryS":"tv_shows","magnet":"?xt=urn:btih:652f253ade161758064f4728b9ae0dd6c22f5126&amp;dn=Bondi.Vet.S05E09.MQwebrip.xvid-%5D%5B+Chris+out+on+the+Farm%2C+Labour+&amp;tr=udp%3A%2F%2Ftracker.openbittorrent.com%3A80&amp;tr=udp%3A%2F%2Fopen.demonii.com%3A1337&amp;tr=udp%3A%2F%2Ftracker.coppersurfer.tk%3A6969&amp;tr=udp%3A%2F%2Fexodus.desync.com%3A6969","seeders":0,"leechers":0,"uploader":"psspss","files":1,"time":1367762036,"description":"Bondi.Vet.S05E09.MQwebrip.xvid-][ Chris out on the Farm, Labour Pains &amp; Scaredy-Donor Cop Dog ].avi\n\nOK I finally did another episode.. help seed it as im running out of data again\nso your lucky im sharing it as 350mb is one less thing I can download too\n\n\nconverted a webstream mp4 800bit rate and 353p to xvid 360p mp3 cbr 128 1000BR\nso quality is OK but not crisp\n\noptimized for sam and sony smart tv play back\n\n\nEnjpy and HELP SEED!","torrent":{"xt":"urn:btih:652f253ade161758064f4728b9ae0dd6c22f5126","amp;dn":"Bondi.Vet.S05E09.MQwebrip.xvid-%5D%5B+Chris+out+on+the+Farm%2C+Labour+","amp;tr":["udp%3A%2F%2Ftracker.openbittorrent.com%3A80","udp%3A%2F%2Fopen.demonii.com%3A1337","udp%3A%2F%2Ftracker.coppersurfer.tk%3A6969","udp%3A%2F%2Fexodus.desync.com%3A6969"],"infoHash":"652f253ade161758064f4728b9ae0dd6c22f5126","infoHashBuffer":{"type":"Buffer","data":[101,47,37,58,222,22,23,88,6,79,71,40,185,174,13,214,194,47,81,38]},"announce":[],"urlList":[]}}