{"title":"Raja Rani Teaser ft. Arya &amp; Nayanthara","uid":8463297,"size":13721155,"categoryP":"video","categoryS":"movie_clips","magnet":"?xt=urn:btih:684fd13a68d14ff5b31c7e0c275528d19134f691&amp;dn=Raja+Rani+Teaser+ft.+Arya+%26amp%3B+Nayanthara&amp;tr=udp%3A%2F%2Ftracker.openbittorrent.com%3A80&amp;tr=udp%3A%2F%2Fopen.demonii.com%3A1337&amp;tr=udp%3A%2F%2Ftracker.coppersurfer.tk%3A6969&amp;tr=udp%3A%2F%2Fexodus.desync.com%3A6969","seeders":0,"leechers":0,"uploader":"AGENT_08","files":1,"time":1368295971,"description":"Raja Rani Teaser ft. Arya &amp; Nayanthara","torrent":{"xt":"urn:btih:684fd13a68d14ff5b31c7e0c275528d19134f691","amp;dn":"Raja+Rani+Teaser+ft.+Arya+%26amp%3B+Nayanthara","amp;tr":["udp%3A%2F%2Ftracker.openbittorrent.com%3A80","udp%3A%2F%2Fopen.demonii.com%3A1337","udp%3A%2F%2Ftracker.coppersurfer.tk%3A6969","udp%3A%2F%2Fexodus.desync.com%3A6969"],"infoHash":"684fd13a68d14ff5b31c7e0c275528d19134f691","infoHashBuffer":{"type":"Buffer","data":[104,79,209,58,104,209,79,245,179,28,126,12,39,85,40,209,145,52,246,145]},"announce":[],"urlList":[]}}