{"title":"Cracking.Crime.Cold.Cases.Ep03.Antoinette.Smith","uid":8440627,"size":124322840,"categoryP":"video","categoryS":"tv_shows","magnet":"?xt=urn:btih:68c41ac986a760be1f8864e1c53eb6ee84ccdd96&amp;dn=Cracking.Crime.Cold.Cases.Ep03.Antoinette.Smith&amp;tr=udp%3A%2F%2Ftracker.openbittorrent.com%3A80&amp;tr=udp%3A%2F%2Fopen.demonii.com%3A1337&amp;tr=udp%3A%2F%2Ftracker.coppersurfer.tk%3A6969&amp;tr=udp%3A%2F%2Fexodus.desync.com%3A6969","seeders":0,"leechers":0,"uploader":"verovenlo","files":1,"time":1367762941,"description":"\n\n\nThe case of Antoinette Smith, who disappeared in July 1987 after attending a David Bowie concert at Slane Castle, Co Meath. \nNine months later her body was found by a family walking through Killakee woods in the Dublin mountains, \nand a taxi driver subsequently gave an account of a woman fitting her description travelling in his vehicle to the outskirts of Rathfarnham village with two men.\n","torrent":{"xt":"urn:btih:68c41ac986a760be1f8864e1c53eb6ee84ccdd96","amp;dn":"Cracking.Crime.Cold.Cases.Ep03.Antoinette.Smith","amp;tr":["udp%3A%2F%2Ftracker.openbittorrent.com%3A80","udp%3A%2F%2Fopen.demonii.com%3A1337","udp%3A%2F%2Ftracker.coppersurfer.tk%3A6969","udp%3A%2F%2Fexodus.desync.com%3A6969"],"infoHash":"68c41ac986a760be1f8864e1c53eb6ee84ccdd96","infoHashBuffer":{"type":"Buffer","data":[104,196,26,201,134,167,96,190,31,136,100,225,197,62,182,238,132,204,221,150]},"announce":[],"urlList":[]}}