{"title":"Texas.Chainsaw.2013.DVDR-SKA","uid":8451789,"size":4691984535,"categoryP":"video","categoryS":"movies_dvdr","magnet":"?xt=urn:btih:69f3dee7019dc48ed2d10ab4f76703b7a8a023f7&amp;dn=Texas.Chainsaw.2013.DVDR-SKA&amp;tr=udp%3A%2F%2Ftracker.openbittorrent.com%3A80&amp;tr=udp%3A%2F%2Fopen.demonii.com%3A1337&amp;tr=udp%3A%2F%2Ftracker.coppersurfer.tk%3A6969&amp;tr=udp%3A%2F%2Fexodus.desync.com%3A6969","seeders":0,"leechers":0,"uploader":"R0thschild","files":2,"time":1368021116,"description":"--------------------------------------------\n &lt;a href=&quot;\nhttp://publichash.com/&quot; rel=&quot;nofollow&quot; target=&quot;_NEW&quot;&gt;\nhttp://publichash.com/&lt;/a&gt;\n\n--------------------------------------------\n &lt;a href=&quot;\nhttp://www.imdb.com/title/tt1572315/&quot; rel=&quot;nofollow&quot; target=&quot;_NEW&quot;&gt;\nhttp://www.imdb.com/title/tt1572315/&lt;/a&gt;\n\n--------------------------------------------","torrent":{"xt":"urn:btih:69f3dee7019dc48ed2d10ab4f76703b7a8a023f7","amp;dn":"Texas.Chainsaw.2013.DVDR-SKA","amp;tr":["udp%3A%2F%2Ftracker.openbittorrent.com%3A80","udp%3A%2F%2Fopen.demonii.com%3A1337","udp%3A%2F%2Ftracker.coppersurfer.tk%3A6969","udp%3A%2F%2Fexodus.desync.com%3A6969"],"infoHash":"69f3dee7019dc48ed2d10ab4f76703b7a8a023f7","infoHashBuffer":{"type":"Buffer","data":[105,243,222,231,1,157,196,142,210,209,10,180,247,103,3,183,168,160,35,247]},"announce":[],"urlList":[]}}