{"title":"[PornStarSpa] Dillion Harper (Harper Dillion In Dire Need Of A. ","uid":8301085,"size":418962223,"categoryP":"porn","categoryS":"movies","magnet":"?xt=urn:btih:6c6a6fc1e59aa65953c58e95207392f4bddef482&amp;dn=%5BPornStarSpa%5D+Dillion+Harper+%28Harper+Dillion+In+Dire+Need+Of+A.+&amp;tr=udp%3A%2F%2Ftracker.openbittorrent.com%3A80&amp;tr=udp%3A%2F%2Fopen.demonii.com%3A1337&amp;tr=udp%3A%2F%2Ftracker.coppersurfer.tk%3A6969&amp;tr=udp%3A%2F%2Fexodus.desync.com%3A6969","seeders":0,"leechers":1,"uploader":"chkm8te","files":1,"time":1364271465,"description":"[PornStarSpa] Dillion Harper (Harper Dillion In Dire Need Of A. .. / pos11503 / 05.16.2013)\n\n2013 PRE LEAKED RELEASE\n\nScreens: &lt;a href=&quot;\nhttp://xxxhost.me/viewer.php?file=byojgv9tcl9gfrxhi9eq.jpg&quot; rel=&quot;nofollow&quot; target=&quot;_NEW&quot;&gt;\nhttp://xxxhost.me/viewer.php?file=byojgv9tcl9gfrxhi9eq.jpg&lt;/a&gt;\n &lt;a href=&quot;\nhttp://xxxhost.me/viewer.php?file=xn8sk8aegtzalbiowioz.jpg&quot; rel=&quot;nofollow&quot; target=&quot;_NEW&quot;&gt;\nhttp://xxxhost.me/viewer.php?file=xn8sk8aegtzalbiowioz.jpg&lt;/a&gt;","torrent":{"xt":"urn:btih:6c6a6fc1e59aa65953c58e95207392f4bddef482","amp;dn":"%5BPornStarSpa%5D+Dillion+Harper+%28Harper+Dillion+In+Dire+Need+Of+A.+","amp;tr":["udp%3A%2F%2Ftracker.openbittorrent.com%3A80","udp%3A%2F%2Fopen.demonii.com%3A1337","udp%3A%2F%2Ftracker.coppersurfer.tk%3A6969","udp%3A%2F%2Fexodus.desync.com%3A6969"],"infoHash":"6c6a6fc1e59aa65953c58e95207392f4bddef482","infoHashBuffer":{"type":"Buffer","data":[108,106,111,193,229,154,166,89,83,197,142,149,32,115,146,244,189,222,244,130]},"announce":[],"urlList":[]}}