{"title":"Indian Desi Exclusive 2013 &amp;ndash; Hard Desi Sex","uid":8275624,"size":457829386,"categoryP":"porn","categoryS":"movie_clips","magnet":"?xt=urn:btih:932ee4940de8b2beaee4f4ef24f60530d32e3490&amp;dn=Indian+Desi+Exclusive+2013+%26ndash%3B+Hard+Desi+Sex&amp;tr=udp%3A%2F%2Ftracker.openbittorrent.com%3A80&amp;tr=udp%3A%2F%2Fopen.demonii.com%3A1337&amp;tr=udp%3A%2F%2Ftracker.coppersurfer.tk%3A6969&amp;tr=udp%3A%2F%2Fexodus.desync.com%3A6969","seeders":0,"leechers":0,"uploader":"StePa644","files":1,"time":1363709969,"description":"Preview:\n   &lt;a href=&quot;\nhttp://desisexblog.net/indian-desi-exclusive-2013-hard-desi-sex/&quot; rel=&quot;nofollow&quot; target=&quot;_NEW&quot;&gt;\nhttp://desisexblog.net/indian-desi-exclusive-2013-hard-desi-sex/&lt;/a&gt;\n\n\nXXX Torrents:\n   &lt;a href=&quot;\nhttp://thepiratebay.se/user/StePa644/&quot; rel=&quot;nofollow&quot; target=&quot;_NEW&quot;&gt;\nhttp://thepiratebay.se/user/StePa644/&lt;/a&gt;","torrent":{"xt":"urn:btih:932ee4940de8b2beaee4f4ef24f60530d32e3490","amp;dn":"Indian+Desi+Exclusive+2013+%26ndash%3B+Hard+Desi+Sex","amp;tr":["udp%3A%2F%2Ftracker.openbittorrent.com%3A80","udp%3A%2F%2Fopen.demonii.com%3A1337","udp%3A%2F%2Ftracker.coppersurfer.tk%3A6969","udp%3A%2F%2Fexodus.desync.com%3A6969"],"infoHash":"932ee4940de8b2beaee4f4ef24f60530d32e3490","infoHashBuffer":{"type":"Buffer","data":[147,46,228,148,13,232,178,190,174,228,244,239,36,246,5,48,211,46,52,144]},"announce":[],"urlList":[]}}