{"title":"Fried.Green.Tomatoes.1991.720p.WEB-DL.x264-mSD","uid":8407299,"size":2565746879,"categoryP":"video","categoryS":"hd___movies","magnet":"?xt=urn:btih:b0e3506da0d5eed0bbe6a684976c6a1c217c49b2&amp;dn=Fried.Green.Tomatoes.1991.720p.WEB-DL.x264-mSD&amp;tr=udp%3A%2F%2Ftracker.openbittorrent.com%3A80&amp;tr=udp%3A%2F%2Fopen.demonii.com%3A1337&amp;tr=udp%3A%2F%2Ftracker.coppersurfer.tk%3A6969&amp;tr=udp%3A%2F%2Fexodus.desync.com%3A6969","seeders":0,"leechers":2,"uploader":"sceneline","files":4,"time":1366829333,"description":"-\n &lt;a href=&quot;\nhttp://www.Speed.&quot; rel=&quot;nofollow&quot; target=&quot;_NEW&quot;&gt;\nhttp://www.Speed.&lt;/a&gt; Cd       the fast  and The Hottest Private Tracker on the net &lt;a href=&quot;\nhttp://www.Speed.&quot; rel=&quot;nofollow&quot; target=&quot;_NEW&quot;&gt;\nhttp://www.Speed.&lt;/a&gt; Cd\n\nPlease Seed back to make the speed Faster!!\n ............ NFO .............\n-\n &lt;a href=&quot;\nhttp://www.Speed.&quot; rel=&quot;nofollow&quot; target=&quot;_NEW&quot;&gt;\nhttp://www.Speed.&lt;/a&gt; Cd[color=blue][b]\nFried.Green.Tomatoes.1991.720p.WEB-DL.x264-mSD [MKV 2.39GB]\n[/b][/color] \n\n \n\n\n[pre]...............................................\n. Fried.Green.Tomatoes.1991.720p.WEB-DL.x264-mSD.mkv\n.......................................\n. Duration        :: 130 Minutes\n. Release Size    :: 2.39GB (52% Compress)\n. x264 r2273      :: 2 198 Kbps\n. Resolution (AR) :: 1280x692 (1.850)\n. Audio Streams   :: AC3 6ch English\n. Subtitles       :: (English)\n. Chapters        :: Yes!\n....................\n\nSource : Fried.Green.Tomatoes.1991.1080p.WEB-DL.DD5.1.h264-iDLE : 4.94GB\n\nraw info: 1280x692p 0:0 @ 10000000/417083 fps (cfr)\nx264 info: profile High, level 4.1\nx264 info: frame I:1244  Avg QP:17.97  size: 91633\nx264 info: frame P:49030 Avg QP:21.24  size: 24318\nx264 info: frame B:137071 Avg QP:24.16  size:  6439\nx264 info: consecutive B-frames:  1.9%  5.1%  5.2% 71.6%  5.3%  8.2%  1.1%  1.3%  0.4%\nencoded 187345 frames, 14.92 fps, 2240.99 kb/s\n","torrent":{"xt":"urn:btih:b0e3506da0d5eed0bbe6a684976c6a1c217c49b2","amp;dn":"Fried.Green.Tomatoes.1991.720p.WEB-DL.x264-mSD","amp;tr":["udp%3A%2F%2Ftracker.openbittorrent.com%3A80","udp%3A%2F%2Fopen.demonii.com%3A1337","udp%3A%2F%2Ftracker.coppersurfer.tk%3A6969","udp%3A%2F%2Fexodus.desync.com%3A6969"],"infoHash":"b0e3506da0d5eed0bbe6a684976c6a1c217c49b2","infoHashBuffer":{"type":"Buffer","data":[176,227,80,109,160,213,238,208,187,230,166,132,151,108,106,28,33,124,73,178]},"announce":[],"urlList":[]}}