{"title":"ATK Exotics - Juicy Delight jui001 - 2 - 1019 pics in 9 sets","uid":8276516,"size":970033307,"categoryP":"porn","categoryS":"pictures","magnet":"?xt=urn:btih:b64c6351fd3d962f755bae9057e57b65af843ad2&amp;dn=ATK+Exotics+-+Juicy+Delight+jui001+-+2+-+1019+pics+in+9+sets&amp;tr=udp%3A%2F%2Ftracker.openbittorrent.com%3A80&amp;tr=udp%3A%2F%2Fopen.demonii.com%3A1337&amp;tr=udp%3A%2F%2Ftracker.coppersurfer.tk%3A6969&amp;tr=udp%3A%2F%2Fexodus.desync.com%3A6969","seeders":0,"leechers":0,"uploader":"bestec1234","files":-1,"time":1363726372,"description":" &lt;a href=&quot;http://bayimg.com/tag/jui001/&quot; rel=&quot;nofollow&quot; target=&quot;_NEW&quot;&gt;http://bayimg.com/tag/jui001/&lt;/a&gt;\n\nTo see the previews, you may have to check 'No I don't mind offensive material' under 'Settings' on bayimg.\n\n\n--\nIn heaven, you can upload a constant stream of new torrents of every shape and size.  They never die and thousands of people download them and leave comments about how awesome you are for uploading them.  You have unlimited bandwidth and so do all of your leechers.  It's a glorious unending cornucopia of ones and zeros flying around in a beautiful orgasmic frenzy of light and energy.  There's no downtime, no limits, and no restrictions.  And also, they have free donuts.","torrent":{"xt":"urn:btih:b64c6351fd3d962f755bae9057e57b65af843ad2","amp;dn":"ATK+Exotics+-+Juicy+Delight+jui001+-+2+-+1019+pics+in+9+sets","amp;tr":["udp%3A%2F%2Ftracker.openbittorrent.com%3A80","udp%3A%2F%2Fopen.demonii.com%3A1337","udp%3A%2F%2Ftracker.coppersurfer.tk%3A6969","udp%3A%2F%2Fexodus.desync.com%3A6969"],"infoHash":"b64c6351fd3d962f755bae9057e57b65af843ad2","infoHashBuffer":{"type":"Buffer","data":[182,76,99,81,253,61,150,47,117,91,174,144,87,229,123,101,175,132,58,210]},"announce":[],"urlList":[]}}