{"title":"NBA.2013.WCSF.G4.(13 may).MIA.Heat.v.CHI.Bulls.720p","uid":8472716,"size":1934530237,"categoryP":"video","categoryS":"hd___tv_shows","magnet":"?xt=urn:btih:ba4c8a629f32386ba381e1e252563707ed56d4d2&amp;dn=NBA.2013.WCSF.G4.%2813+may%29.MIA.Heat.v.CHI.Bulls.720p&amp;tr=udp%3A%2F%2Ftracker.openbittorrent.com%3A80&amp;tr=udp%3A%2F%2Fopen.demonii.com%3A1337&amp;tr=udp%3A%2F%2Ftracker.coppersurfer.tk%3A6969&amp;tr=udp%3A%2F%2Fexodus.desync.com%3A6969","seeders":0,"leechers":0,"uploader":"Nepotu","files":1,"time":1368525988,"description":"Playoffs game no. 59 (including G1, 2&amp;3)\n\nCredit: jaguar777","torrent":{"xt":"urn:btih:ba4c8a629f32386ba381e1e252563707ed56d4d2","amp;dn":"NBA.2013.WCSF.G4.%2813+may%29.MIA.Heat.v.CHI.Bulls.720p","amp;tr":["udp%3A%2F%2Ftracker.openbittorrent.com%3A80","udp%3A%2F%2Fopen.demonii.com%3A1337","udp%3A%2F%2Ftracker.coppersurfer.tk%3A6969","udp%3A%2F%2Fexodus.desync.com%3A6969"],"infoHash":"ba4c8a629f32386ba381e1e252563707ed56d4d2","infoHashBuffer":{"type":"Buffer","data":[186,76,138,98,159,50,56,107,163,129,225,226,82,86,55,7,237,86,212,210]},"announce":[],"urlList":[]}}