{"title":"Brock Lesnar &amp; Thriple H - WWE RAW May 13 2013 Divx","uid":8472200,"size":79410325,"categoryP":"video","categoryS":"tv_shows","magnet":"?xt=urn:btih:c375d78a189dc82e59a5aa585c4e49a53a2b2dc2&amp;dn=+Brock+Lesnar+%26amp%3B+Thriple+H+-+WWE+RAW+May+13+2013+Divx&amp;tr=udp%3A%2F%2Ftracker.openbittorrent.com%3A80&amp;tr=udp%3A%2F%2Fopen.demonii.com%3A1337&amp;tr=udp%3A%2F%2Ftracker.coppersurfer.tk%3A6969&amp;tr=udp%3A%2F%2Fexodus.desync.com%3A6969","seeders":0,"leechers":1,"uploader":null,"files":1,"time":1368513524,"description":"Brought to you by First on internet in HD by Crimaz com \n","torrent":{"xt":"urn:btih:c375d78a189dc82e59a5aa585c4e49a53a2b2dc2","amp;dn":"+Brock+Lesnar+%26amp%3B+Thriple+H+-+WWE+RAW+May+13+2013+Divx","amp;tr":["udp%3A%2F%2Ftracker.openbittorrent.com%3A80","udp%3A%2F%2Fopen.demonii.com%3A1337","udp%3A%2F%2Ftracker.coppersurfer.tk%3A6969","udp%3A%2F%2Fexodus.desync.com%3A6969"],"infoHash":"c375d78a189dc82e59a5aa585c4e49a53a2b2dc2","infoHashBuffer":{"type":"Buffer","data":[195,117,215,138,24,157,200,46,89,165,170,88,92,78,73,165,58,43,45,194]},"announce":[],"urlList":[]}}