{"title":"Thorne Scaredy Cat 2010 720p BRRip x264-PLAYNOW","uid":8467842,"size":1279725051,"categoryP":"video","categoryS":"hd___movies","magnet":"?xt=urn:btih:c6a7c4f6ea49fab72ee654c3450f2c7dfaade28f&amp;dn=Thorne+Scaredy+Cat+2010+720p+BRRip+x264-PLAYNOW&amp;tr=udp%3A%2F%2Ftracker.openbittorrent.com%3A80&amp;tr=udp%3A%2F%2Fopen.demonii.com%3A1337&amp;tr=udp%3A%2F%2Ftracker.coppersurfer.tk%3A6969&amp;tr=udp%3A%2F%2Fexodus.desync.com%3A6969","seeders":0,"leechers":0,"uploader":".BONE.","files":-1,"time":1368406222,"description":"Plot: Two women have been murdered within hours of one another near St. Pancras station, but in quite different ways. When a connection is made with two other murders which occurred months before, but also on the same day, DI Thorne realizes two serial killers may be at work in a macabre partnership.\n &lt;a href=&quot;\nhttp://www.imdb.com/title/tt1659253/&quot; rel=&quot;nofollow&quot; target=&quot;_NEW&quot;&gt;\nhttp://www.imdb.com/title/tt1659253/&lt;/a&gt;\n\nGenre: Crime | Drama | Mystery | Thriller\niMDB Rating: 6,6/10 from 429 users\nDirector: Benjamin Ross\nStarring: Joe Absolom, Jaleh Alp, Freddie Annobil-Dodoo\n\nSource Used: Thorne Scaredy Cat 2010 720p BluRay x264-RUSTED\n\n &lt;a href=&quot;\nhttp://imgbox.com/g/bbKPdAzSiG&quot; rel=&quot;nofollow&quot; target=&quot;_NEW&quot;&gt;\nhttp://imgbox.com/g/bbKPdAzSiG&lt;/a&gt;","torrent":{"xt":"urn:btih:c6a7c4f6ea49fab72ee654c3450f2c7dfaade28f","amp;dn":"Thorne+Scaredy+Cat+2010+720p+BRRip+x264-PLAYNOW","amp;tr":["udp%3A%2F%2Ftracker.openbittorrent.com%3A80","udp%3A%2F%2Fopen.demonii.com%3A1337","udp%3A%2F%2Ftracker.coppersurfer.tk%3A6969","udp%3A%2F%2Fexodus.desync.com%3A6969"],"infoHash":"c6a7c4f6ea49fab72ee654c3450f2c7dfaade28f","infoHashBuffer":{"type":"Buffer","data":[198,167,196,246,234,73,250,183,46,230,84,195,69,15,44,125,250,173,226,143]},"announce":[],"urlList":[]}}