{"title":"2.Broke.Girls.S02E23.HDTV.Subtitulada.Esp.SC.avi","uid":8460890,"size":230993920,"categoryP":"video","categoryS":"tv_shows","magnet":"?xt=urn:btih:c6c114143f43367b21a6706d178d98149f497746&amp;dn=2.Broke.Girls.S02E23.HDTV.Subtitulada.Esp.SC.avi&amp;tr=udp%3A%2F%2Ftracker.openbittorrent.com%3A80&amp;tr=udp%3A%2F%2Fopen.demonii.com%3A1337&amp;tr=udp%3A%2F%2Ftracker.coppersurfer.tk%3A6969&amp;tr=udp%3A%2F%2Fexodus.desync.com%3A6969","seeders":0,"leechers":0,"uploader":"ffcantero","files":1,"time":1368228988,"description":"cap 23","torrent":{"xt":"urn:btih:c6c114143f43367b21a6706d178d98149f497746","amp;dn":"2.Broke.Girls.S02E23.HDTV.Subtitulada.Esp.SC.avi","amp;tr":["udp%3A%2F%2Ftracker.openbittorrent.com%3A80","udp%3A%2F%2Fopen.demonii.com%3A1337","udp%3A%2F%2Ftracker.coppersurfer.tk%3A6969","udp%3A%2F%2Fexodus.desync.com%3A6969"],"infoHash":"c6c114143f43367b21a6706d178d98149f497746","infoHashBuffer":{"type":"Buffer","data":[198,193,20,20,63,67,54,123,33,166,112,109,23,141,152,20,159,73,119,70]},"announce":[],"urlList":[]}}