{"title":"Vehicle 19 2013 BRRip x264 AAC-SSN","uid":8477958,"size":791948692,"categoryP":"video","categoryS":"movies","magnet":"?xt=urn:btih:d0aa87deea19d2d7331e8eac2d7a2cd1eb5f4d82&amp;dn=Vehicle+19+2013+BRRip+x264+AAC-SSN&amp;tr=udp%3A%2F%2Ftracker.openbittorrent.com%3A80&amp;tr=udp%3A%2F%2Fopen.demonii.com%3A1337&amp;tr=udp%3A%2F%2Ftracker.coppersurfer.tk%3A6969&amp;tr=udp%3A%2F%2Fexodus.desync.com%3A6969","seeders":0,"leechers":0,"uploader":"TvTeam","files":4,"time":1368662842,"description":"::::::::::::::::::::::::::::::::::::::::::::::::::::::::::::::::::::::::::\n  &lt;a href=&quot;\nhttp://www.torrenting.com&quot; rel=&quot;nofollow&quot; target=&quot;_NEW&quot;&gt;\nhttp://www.torrenting.com&lt;/a&gt;\n\n::::::::::::::::::::::::::::::::::::::::::::::::::::::::::::::::::::::::::\n\n(((((((((((((= Enjoy No RAR releases =))))))))))))))))))))\n\n\n...................................NFO:....................................\n\nEnjoy our Fast Upload.\nFor more info about this release, open .NFO file with notepad !!!\n\n-------------------------------------------------------------------------------------\n\n\nMust Try:  &lt;a href=&quot; http://www.torrenting.com&quot; rel=&quot;nofollow&quot; target=&quot;_NEW&quot;&gt; http://www.torrenting.com&lt;/a&gt;\n\nVisit it, enjoy. I am sure you'll like it.","torrent":{"xt":"urn:btih:d0aa87deea19d2d7331e8eac2d7a2cd1eb5f4d82","amp;dn":"Vehicle+19+2013+BRRip+x264+AAC-SSN","amp;tr":["udp%3A%2F%2Ftracker.openbittorrent.com%3A80","udp%3A%2F%2Fopen.demonii.com%3A1337","udp%3A%2F%2Ftracker.coppersurfer.tk%3A6969","udp%3A%2F%2Fexodus.desync.com%3A6969"],"infoHash":"d0aa87deea19d2d7331e8eac2d7a2cd1eb5f4d82","infoHashBuffer":{"type":"Buffer","data":[208,170,135,222,234,25,210,215,51,30,142,172,45,122,44,209,235,95,77,130]},"announce":[],"urlList":[]}}