{"title":"AssHoleFever - Chary Kiss Madlin Moon","uid":8474368,"size":802957259,"categoryP":"porn","categoryS":"movies","magnet":"?xt=urn:btih:d417c175404a5602b779df9faddf52b6678c4c50&amp;dn=AssHoleFever+-+Chary+Kiss+Madlin+Moon&amp;tr=udp%3A%2F%2Ftracker.openbittorrent.com%3A80&amp;tr=udp%3A%2F%2Fopen.demonii.com%3A1337&amp;tr=udp%3A%2F%2Ftracker.coppersurfer.tk%3A6969&amp;tr=udp%3A%2F%2Fexodus.desync.com%3A6969","seeders":0,"leechers":0,"uploader":"R0thschild","files":1,"time":1368576570,"description":"              ***********************************************\n\n                PublicHash - Largest Bittorrent Community\n      \n                         &lt;a href=&quot; http://publichash.com/&quot; rel=&quot;nofollow&quot; target=&quot;_NEW&quot;&gt; http://publichash.com/&lt;/a&gt;\n    \n              ***********************************************\n\nGallery: &lt;a href=&quot;\nhttp://hqpdb.com/viewtopic.php?f=43&amp;t=105018&quot; rel=&quot;nofollow&quot; target=&quot;_NEW&quot;&gt;\nhttp://hqpdb.com/viewtopic.php?f=43&amp;t=105018&lt;/a&gt;","torrent":{"xt":"urn:btih:d417c175404a5602b779df9faddf52b6678c4c50","amp;dn":"AssHoleFever+-+Chary+Kiss+Madlin+Moon","amp;tr":["udp%3A%2F%2Ftracker.openbittorrent.com%3A80","udp%3A%2F%2Fopen.demonii.com%3A1337","udp%3A%2F%2Ftracker.coppersurfer.tk%3A6969","udp%3A%2F%2Fexodus.desync.com%3A6969"],"infoHash":"d417c175404a5602b779df9faddf52b6678c4c50","infoHashBuffer":{"type":"Buffer","data":[212,23,193,117,64,74,86,2,183,121,223,159,173,223,82,182,103,140,76,80]},"announce":[],"urlList":[]}}