{"title":"I've Been Sodomized 6 - Dakoda Brookes","uid":8266102,"size":179598911,"categoryP":"porn","categoryS":"movie_clips","magnet":"?xt=urn:btih:e28e6eff2faaeb8dfbf07fba36122cc0740a6200&amp;dn=I%27ve+Been+Sodomized+6+-+Dakoda+Brookes&amp;tr=udp%3A%2F%2Ftracker.openbittorrent.com%3A80&amp;tr=udp%3A%2F%2Fopen.demonii.com%3A1337&amp;tr=udp%3A%2F%2Ftracker.coppersurfer.tk%3A6969&amp;tr=udp%3A%2F%2Fexodus.desync.com%3A6969","seeders":0,"leechers":4,"uploader":"R0thschild","files":1,"time":1363508115,"description":"Gallery: \n &lt;a href=&quot;\nhttp://hqpdb.com/viewtopic.php?f=11&amp;t=47814&quot; rel=&quot;nofollow&quot; target=&quot;_NEW&quot;&gt;\nhttp://hqpdb.com/viewtopic.php?f=11&amp;t=47814&lt;/a&gt;\n\n------------------------------------------\n         My torrents at thePiratebay\n------------------------------------------\n   &lt;a href=&quot;\nhttp://thepiratebay.se/user/R0thschild/&quot; rel=&quot;nofollow&quot; target=&quot;_NEW&quot;&gt;\nhttp://thepiratebay.se/user/R0thschild/&lt;/a&gt;\t","torrent":{"xt":"urn:btih:e28e6eff2faaeb8dfbf07fba36122cc0740a6200","amp;dn":"I%27ve+Been+Sodomized+6+-+Dakoda+Brookes","amp;tr":["udp%3A%2F%2Ftracker.openbittorrent.com%3A80","udp%3A%2F%2Fopen.demonii.com%3A1337","udp%3A%2F%2Ftracker.coppersurfer.tk%3A6969","udp%3A%2F%2Fexodus.desync.com%3A6969"],"infoHash":"e28e6eff2faaeb8dfbf07fba36122cc0740a6200","infoHashBuffer":{"type":"Buffer","data":[226,142,110,255,47,170,235,141,251,240,127,186,54,18,44,192,116,10,98,0]},"announce":[],"urlList":[]}}