{"title":"Black Anal Addiction 2 (Disc 1+2) XXX DVDRip NEW (2013)","uid":8349894,"size":3589545134,"categoryP":"porn","categoryS":"movies","magnet":"?xt=urn:btih:f92ec13213a2732ccac366f2662b6b50aeddf3ac&amp;dn=Black+Anal+Addiction+2+%28Disc+1%2B2%29+XXX+DVDRip+NEW+%282013%29&amp;tr=udp%3A%2F%2Ftracker.openbittorrent.com%3A80&amp;tr=udp%3A%2F%2Fopen.demonii.com%3A1337&amp;tr=udp%3A%2F%2Ftracker.coppersurfer.tk%3A6969&amp;tr=udp%3A%2F%2Fexodus.desync.com%3A6969","seeders":0,"leechers":1,"uploader":"xuluhulu","files":2,"time":1365307022,"description":"The luckiest white boy on Earth, ass-obsessed director Mike Adriano, is back in black! His latest two-disc backdoor bash, 'Black Anal Addiction #2,' explores interracial butt fucking and insane rectal hijinks with gorgeous Nubian models. These stunning black goddesses are eager for every sort of twisted anal perversion, and their dusky beauty is only matched by their insatiable hunger for Caucasian cock! Ana Foxxx, a slender ebony babe in white fishnets, worships the director's dork in a wet, gagging blow job. She gets her rectum reamed until it gapes, exposing the glistening pink meat inside, before opening wide for a creamy cum treat!\n\nNext, dark chocolate bombshell Tatiyana Foxx wraps her full lips around Mike's tool, rims his bunghole and spreads her thick ass cheeks for a thorough butt pounding. Sweet and curvaceous Janea Jolie offers her exquisite ass for Mike's raging member. She submissively slurps his pole ass-to-mouth, and he oils her buttocks until they glisten while he's wrecking Janea's flawless booty. Skinny, light-skinned MILF Farah Faye is fairly new to the game. Loosening her sphincter with a large dildo, she gets her colon expanded for the director's throbbing joint. And she gets her face splattered with hot goo. Finally, Ana Foxxx returns for a nasty anal three-way with glamorous caramel cutie Yasmine de Leon. Plus there's a filthy, long bonus scene with luscious Coffee Brown (from the first release in the series). 'Black Anal Addiction #2' is an irresistible craving you just can't quit!\n\nCOVERS:\n &lt;a href=&quot;\nhttp://www.imgnip.com/viewer.php?file=97099972308891916050.jpg&quot; rel=&quot;nofollow&quot; target=&quot;_NEW&quot;&gt;\nhttp://www.imgnip.com/viewer.php?file=97099972308891916050.jpg&lt;/a&gt;\n &lt;a href=&quot;\nhttp://www.imgnip.com/viewer.php?file=03965198351687413231.jpg&quot; rel=&quot;nofollow&quot; target=&quot;_NEW&quot;&gt;\nhttp://www.imgnip.com/viewer.php?file=03965198351687413231.jpg&lt;/a&gt;\n\n\nTHUMBSNAIL SCREENS:\n &lt;a href=&quot;\nhttp://www.imgnip.com/viewer.php?file=03729851667561125225.jpg&quot; rel=&quot;nofollow&quot; target=&quot;_NEW&quot;&gt;\nhttp://www.imgnip.com/viewer.php?file=03729851667561125225.jpg&lt;/a&gt;\n &lt;a href=&quot;\nhttp://www.imgnip.com/viewer.php?file=07995953225845548712.jpg&quot; rel=&quot;nofollow&quot; target=&quot;_NEW&quot;&gt;\nhttp://www.imgnip.com/viewer.php?file=07995953225845548712.jpg&lt;/a&gt;\n\n\nCAST:\n\nAna Foxx, Coffee Brown, Tatiana Fox, Mike Adriano, Yasmine De Leon, Farah Faye, Janea Jolie\n\n\nSEED &amp; ENJOY!!!","torrent":{"xt":"urn:btih:f92ec13213a2732ccac366f2662b6b50aeddf3ac","amp;dn":"Black+Anal+Addiction+2+%28Disc+1%2B2%29+XXX+DVDRip+NEW+%282013%29","amp;tr":["udp%3A%2F%2Ftracker.openbittorrent.com%3A80","udp%3A%2F%2Fopen.demonii.com%3A1337","udp%3A%2F%2Ftracker.coppersurfer.tk%3A6969","udp%3A%2F%2Fexodus.desync.com%3A6969"],"infoHash":"f92ec13213a2732ccac366f2662b6b50aeddf3ac","infoHashBuffer":{"type":"Buffer","data":[249,46,193,50,19,162,115,44,202,195,102,242,102,43,107,80,174,221,243,172]},"announce":[],"urlList":[]}}