{"title":"[Passion-HD] Jessa (Passionate Suduction/ 05.08.2013)","uid":8454055,"size":241314914,"categoryP":"porn","categoryS":"movies","magnet":"?xt=urn:btih:f96b3c69f9c77f7df5c1aef2c542cc94e8dbf824&amp;dn=%5BPassion-HD%5D+Jessa+%28Passionate+Suduction%2F+05.08.2013%29&amp;tr=udp%3A%2F%2Ftracker.openbittorrent.com%3A80&amp;tr=udp%3A%2F%2Fopen.demonii.com%3A1337&amp;tr=udp%3A%2F%2Ftracker.coppersurfer.tk%3A6969&amp;tr=udp%3A%2F%2Fexodus.desync.com%3A6969","seeders":0,"leechers":0,"uploader":"chkm8te","files":1,"time":1368069305,"description":"[Passion-HD] Jessa (Passionate Suduction/ 05.08.2013)\n\nScreens: &lt;a href=&quot;\nhttp://xxxhost.me/viewer.php?file=8hhbe9r9rjj8a5jomz8l.jpg&quot; rel=&quot;nofollow&quot; target=&quot;_NEW&quot;&gt;\nhttp://xxxhost.me/viewer.php?file=8hhbe9r9rjj8a5jomz8l.jpg&lt;/a&gt;\n &lt;a href=&quot;\nhttp://xxxhost.me/viewer.php?file=rzl1p4glfdnxguw7vqu5.jpg&quot; rel=&quot;nofollow&quot; target=&quot;_NEW&quot;&gt;\nhttp://xxxhost.me/viewer.php?file=rzl1p4glfdnxguw7vqu5.jpg&lt;/a&gt;","torrent":{"xt":"urn:btih:f96b3c69f9c77f7df5c1aef2c542cc94e8dbf824","amp;dn":"%5BPassion-HD%5D+Jessa+%28Passionate+Suduction%2F+05.08.2013%29","amp;tr":["udp%3A%2F%2Ftracker.openbittorrent.com%3A80","udp%3A%2F%2Fopen.demonii.com%3A1337","udp%3A%2F%2Ftracker.coppersurfer.tk%3A6969","udp%3A%2F%2Fexodus.desync.com%3A6969"],"infoHash":"f96b3c69f9c77f7df5c1aef2c542cc94e8dbf824","infoHashBuffer":{"type":"Buffer","data":[249,107,60,105,249,199,127,125,245,193,174,242,197,66,204,148,232,219,248,36]},"announce":[],"urlList":[]}}